easyssh.py
easyssh_cli-1.0.0.dist-info/licenses/LICENSE
easyssh_cli-1.0.0.dist-info/METADATA
easyssh_cli-1.0.0.dist-info/WHEEL
easyssh_cli-1.0.0.dist-info/entry_points.txt
easyssh_cli-1.0.0.dist-info/top_level.txt
easyssh_cli-1.0.0.dist-info/RECORD
