Metadata-Version: 2.4
Name: easyssh-cli
Version: 1.0.0
Summary: Un outil CLI élégant pour gérer et se connecter facilement à vos serveurs SSH
Home-page: https://github.com/basile-parent/easyssh
Author: Basile Parent
Author-email: Basile Parent <basile.parent@example.com>
Maintainer-email: Basile Parent <basile.parent@example.com>
License: MIT License
Project-URL: Homepage, https://github.com/basile-parent/easyssh
Project-URL: Bug Reports, https://github.com/basile-parent/easyssh/issues
Project-URL: Source, https://github.com/basile-parent/easyssh
Project-URL: Documentation, https://github.com/basile-parent/easyssh#readme
Keywords: ssh,cli,terminal,server,management,connection
Classifier: Development Status :: 4 - Beta
Classifier: Intended Audience :: Developers
Classifier: Intended Audience :: System Administrators
Classifier: Topic :: System :: Systems Administration
Classifier: Topic :: Utilities
Classifier: License :: OSI Approved :: MIT License
Classifier: Programming Language :: Python :: 3
Classifier: Programming Language :: Python :: 3.7
Classifier: Programming Language :: Python :: 3.8
Classifier: Programming Language :: Python :: 3.9
Classifier: Programming Language :: Python :: 3.10
Classifier: Programming Language :: Python :: 3.11
Classifier: Programming Language :: Python :: 3.12
Classifier: Operating System :: OS Independent
Requires-Python: >=3.7, <4
License-File: LICENSE
Requires-Dist: rich>=13.0.0
Requires-Dist: textual>=0.41.0
Requires-Dist: pyfiglet>=0.8.0
Requires-Dist: colorama>=0.4.0
Requires-Dist: paramiko>=3.0.0
Requires-Dist: click>=8.0.0
Provides-Extra: dev
Requires-Dist: pytest>=6.0; extra == "dev"
Requires-Dist: pytest-cov; extra == "dev"
Requires-Dist: black; extra == "dev"
Requires-Dist: flake8; extra == "dev"
Dynamic: author
Dynamic: home-page
Dynamic: license-file
Dynamic: requires-python
